agentbill/__init__.py
agentbill/autoinstrument.py
agentbill/bulk.py
agentbill/client.py
agentbill/distributed.py
agentbill/exceptions.py
agentbill/ollama_wrapper.py
agentbill/perplexity_wrapper.py
agentbill/signals.py
agentbill/tracer.py
agentbill/tracing.py
agentbill/types.py
agentbill/validation.py
agentbill/wrappers.py
agentbill/resources/__init__.py
agentbill/resources/agents.py
agentbill/resources/contacts.py
agentbill/resources/customers.py
agentbill/resources/orders.py
agentbill/resources/signal_types.py
agentbill_py_sdk-7.17.3.dist-info/licenses/LICENSE
agentbill_py_sdk-7.17.3.dist-info/METADATA
agentbill_py_sdk-7.17.3.dist-info/WHEEL
agentbill_py_sdk-7.17.3.dist-info/top_level.txt
agentbill_py_sdk-7.17.3.dist-info/RECORD
