Metadata-Version: 2.4
Name: agentbill-py-sdk
Version: 7.17.3
Summary: OpenTelemetry-based SDK for tracking and billing AI agent usage with Cost Guard protection
Home-page: https://agentbill.io
Author: AgentBill
Author-email: AgentBill Team <support@agentbill.io>
License: MIT
Project-URL: Homepage, https://agentbill.io
Project-URL: Documentation, https://docs.agentbill.io
Keywords: ai,billing,tracking,opentelemetry,llm,agents,cost-guard,tracing,distributed-tracing
Classifier: Development Status :: 4 - Beta
Classifier: Intended Audience :: Developers
Classifier: License :: OSI Approved :: MIT License
Classifier: Programming Language :: Python :: 3
Classifier: Programming Language :: Python :: 3.8
Classifier: Programming Language :: Python :: 3.9
Classifier: Programming Language :: Python :: 3.10
Classifier: Programming Language :: Python :: 3.11
Classifier: Programming Language :: Python :: 3.12
Requires-Python: >=3.8
License-File: LICENSE
Requires-Dist: httpx>=0.24.0
Provides-Extra: dev
Requires-Dist: pytest>=7.0.0; extra == "dev"
Requires-Dist: pytest-cov>=4.0.0; extra == "dev"
Requires-Dist: black>=23.0.0; extra == "dev"
Requires-Dist: pylint>=2.17.0; extra == "dev"
Requires-Dist: mypy>=1.0.0; extra == "dev"
Dynamic: author
Dynamic: home-page
Dynamic: license-file
Dynamic: requires-python
